spectacular_analysis/__init__.py
spectacular_analysis/example.py
spectacular_analysis/spectacular_code.py
spectacular_analysis-0.0.5.dist-info/LICENSE.txt
spectacular_analysis-0.0.5.dist-info/METADATA
spectacular_analysis-0.0.5.dist-info/WHEEL
spectacular_analysis-0.0.5.dist-info/top_level.txt
spectacular_analysis-0.0.5.dist-info/RECORD
